[
    {
        "epoch": 0,
        "learning_rate": 0.01,
        "batch_size": 32,
        "len_train_indices": 10000,
        "len_test_indices": 2000,
        "momentum": 0.5,
        "train_loss": 1.7139605493210375,
        "train_accuracy": 37.32,
        "test_loss": 1.7062295391446067,
        "test_accuracy": 40.25,
        "path_norm": 120.90883461956987,
        "global_path_norm": 23.147414443305678,
        "timestamp": "2024-11-26T17:13:07.365990"
    },
    {
        "epoch": 1,
        "learning_rate": 0.01,
        "batch_size": 32,
        "len_train_indices": 10000,
        "len_test_indices": 2000,
        "momentum": 0.5,
        "train_loss": 1.361420435075181,
        "train_accuracy": 51.05,
        "test_loss": 1.4586159426068503,
        "test_accuracy": 46.35,
        "path_norm": 127.69460485617628,
        "global_path_norm": 23.147414443305678,
        "timestamp": "2024-11-26T17:14:21.370161"
    },
    {
        "epoch": 2,
        "learning_rate": 0.01,
        "batch_size": 32,
        "len_train_indices": 10000,
        "len_test_indices": 2000,
        "momentum": 0.5,
        "train_loss": 1.154619663858566,
        "train_accuracy": 59.99,
        "test_loss": 1.3656060941635617,
        "test_accuracy": 51.1,
        "path_norm": 133.0722093099269,
        "global_path_norm": 23.147414443305678,
        "timestamp": "2024-11-26T17:15:30.962018"
    },
    {
        "epoch": 0,
        "learning_rate": 0.01,
        "batch_size": 32,
        "len_train_indices": 10000,
        "len_test_indices": 2000,
        "momentum": 0.5,
        "train_loss": 1.2067548051809731,
        "train_accuracy": 57.91,
        "test_loss": 1.4458334379725986,
        "test_accuracy": 51.85,
        "path_norm": 96.66795414911293,
        "global_path_norm": 26.919433199624812,
        "timestamp": "2024-11-26T17:17:32.802630"
    },
    {
        "epoch": 1,
        "learning_rate": 0.01,
        "batch_size": 32,
        "len_train_indices": 10000,
        "len_test_indices": 2000,
        "momentum": 0.5,
        "train_loss": 0.9535843716642727,
        "train_accuracy": 66.55,
        "test_loss": 1.1945758149737404,
        "test_accuracy": 58.9,
        "path_norm": 106.27609054662766,
        "global_path_norm": 26.919433199624812,
        "timestamp": "2024-11-26T17:18:47.098507"
    },
    {
        "epoch": 2,
        "learning_rate": 0.01,
        "batch_size": 32,
        "len_train_indices": 10000,
        "len_test_indices": 2000,
        "momentum": 0.5,
        "train_loss": 0.7796158325938752,
        "train_accuracy": 73.17,
        "test_loss": 1.4502583533998519,
        "test_accuracy": 53.65,
        "path_norm": 118.53325614569103,
        "global_path_norm": 26.919433199624812,
        "timestamp": "2024-11-26T17:19:56.838421"
    },
    {
        "epoch": 0,
        "learning_rate": 0.01,
        "batch_size": 32,
        "len_train_indices": 10000,
        "len_test_indices": 2000,
        "momentum": 0.5,
        "train_loss": 0.8724702147249216,
        "train_accuracy": 69.6,
        "test_loss": 1.3686749064733112,
        "test_accuracy": 56.6,
        "path_norm": 86.30618640920244,
        "global_path_norm": 36.16742514475647,
        "timestamp": "2024-11-26T17:21:54.303346"
    },
    {
        "epoch": 1,
        "learning_rate": 0.01,
        "batch_size": 32,
        "len_train_indices": 10000,
        "len_test_indices": 2000,
        "momentum": 0.5,
        "train_loss": 0.6270749668915051,
        "train_accuracy": 78.86,
        "test_loss": 1.2035907606283824,
        "test_accuracy": 62.0,
        "path_norm": 95.0176587206294,
        "global_path_norm": 36.16742514475647,
        "timestamp": "2024-11-26T17:23:02.349199"
    },
    {
        "epoch": 2,
        "learning_rate": 0.01,
        "batch_size": 32,
        "len_train_indices": 10000,
        "len_test_indices": 2000,
        "momentum": 0.5,
        "train_loss": 0.4657183271913102,
        "train_accuracy": 84.99,
        "test_loss": 1.3011515254066104,
        "test_accuracy": 60.4,
        "path_norm": 108.0710848238325,
        "global_path_norm": 36.16742514475647,
        "timestamp": "2024-11-26T17:24:10.298274"
    },
    {
        "epoch": 0,
        "learning_rate": 0.01,
        "batch_size": 32,
        "len_train_indices": 10000,
        "len_test_indices": 2000,
        "momentum": 0.5,
        "train_loss": 0.6451544033262295,
        "train_accuracy": 77.4,
        "test_loss": 1.3212155671346755,
        "test_accuracy": 62.45,
        "path_norm": 95.38061602895266,
        "global_path_norm": 55.47881950855209,
        "timestamp": "2024-11-26T17:26:24.063705"
    },
    {
        "epoch": 1,
        "learning_rate": 0.01,
        "batch_size": 32,
        "len_train_indices": 10000,
        "len_test_indices": 2000,
        "momentum": 0.5,
        "train_loss": 0.3497572909719266,
        "train_accuracy": 88.24,
        "test_loss": 1.1914070702734447,
        "test_accuracy": 64.2,
        "path_norm": 104.59971599357954,
        "global_path_norm": 55.47881950855209,
        "timestamp": "2024-11-26T17:27:38.268789"
    },
    {
        "epoch": 2,
        "learning_rate": 0.01,
        "batch_size": 32,
        "len_train_indices": 10000,
        "len_test_indices": 2000,
        "momentum": 0.5,
        "train_loss": 0.20188861381940948,
        "train_accuracy": 94.36,
        "test_loss": 1.0845803575856345,
        "test_accuracy": 67.9,
        "path_norm": 111.47840843353927,
        "global_path_norm": 55.47881950855209,
        "timestamp": "2024-11-26T17:28:47.588671"
    },
    {
        "epoch": 0,
        "learning_rate": 0.01,
        "batch_size": 32,
        "len_train_indices": 10000,
        "len_test_indices": 2000,
        "momentum": 0.5,
        "train_loss": 0.4412159448186049,
        "train_accuracy": 84.24,
        "test_loss": 1.3215862266601077,
        "test_accuracy": 64.35,
        "path_norm": 112.17967416994489,
        "global_path_norm": 93.25664457727663,
        "timestamp": "2024-11-26T17:30:46.242762"
    },
    {
        "epoch": 1,
        "learning_rate": 0.01,
        "batch_size": 32,
        "len_train_indices": 10000,
        "len_test_indices": 2000,
        "momentum": 0.5,
        "train_loss": 0.1518950058986394,
        "train_accuracy": 95.76,
        "test_loss": 1.1558851356071138,
        "test_accuracy": 67.45,
        "path_norm": 120.04836265022526,
        "global_path_norm": 93.25664457727663,
        "timestamp": "2024-11-26T17:32:00.199944"
    },
    {
        "epoch": 2,
        "learning_rate": 0.01,
        "batch_size": 32,
        "len_train_indices": 10000,
        "len_test_indices": 2000,
        "momentum": 0.5,
        "train_loss": 0.07532346584259893,
        "train_accuracy": 98.52,
        "test_loss": 1.2923176936686984,
        "test_accuracy": 66.3,
        "path_norm": 125.42584493685901,
        "global_path_norm": 93.25664457727663,
        "timestamp": "2024-11-26T17:33:11.625052"
    },
    {
        "epoch": 0,
        "learning_rate": 0.01,
        "batch_size": 32,
        "len_train_indices": 10000,
        "len_test_indices": 2000,
        "momentum": 0.5,
        "train_loss": 0.26080456708733457,
        "train_accuracy": 90.57,
        "test_loss": 1.3397598730193243,
        "test_accuracy": 69.7,
        "path_norm": 141.42741899557527,
        "global_path_norm": 164.15014325686712,
        "timestamp": "2024-11-26T17:35:14.132517"
    },
    {
        "epoch": 1,
        "learning_rate": 0.01,
        "batch_size": 32,
        "len_train_indices": 10000,
        "len_test_indices": 2000,
        "momentum": 0.5,
        "train_loss": 0.07555277250445308,
        "train_accuracy": 97.81,
        "test_loss": 1.2003038549233997,
        "test_accuracy": 71.2,
        "path_norm": 144.37261226380508,
        "global_path_norm": 164.15014325686712,
        "timestamp": "2024-11-26T17:36:28.370903"
    },
    {
        "epoch": 2,
        "learning_rate": 0.01,
        "batch_size": 32,
        "len_train_indices": 10000,
        "len_test_indices": 2000,
        "momentum": 0.5,
        "train_loss": 0.04001458946871348,
        "train_accuracy": 99.11,
        "test_loss": 1.2483430599409437,
        "test_accuracy": 71.35,
        "path_norm": 148.20143070328302,
        "global_path_norm": 164.15014325686712,
        "timestamp": "2024-11-26T17:37:38.839892"
    },
    {
        "epoch": 0,
        "learning_rate": 0.01,
        "batch_size": 32,
        "len_train_indices": 10000,
        "len_test_indices": 2000,
        "momentum": 0.5,
        "train_loss": 0.13515888782331167,
        "train_accuracy": 95.18,
        "test_loss": 1.3924287084549192,
        "test_accuracy": 69.6,
        "path_norm": 176.3468151647486,
        "global_path_norm": 291.25820803884653,
        "timestamp": "2024-11-26T17:39:39.478507"
    },
    {
        "epoch": 1,
        "learning_rate": 0.01,
        "batch_size": 32,
        "len_train_indices": 10000,
        "len_test_indices": 2000,
        "momentum": 0.5,
        "train_loss": 0.038568626487472904,
        "train_accuracy": 98.99,
        "test_loss": 1.3416149649355147,
        "test_accuracy": 71.3,
        "path_norm": 178.52813481878704,
        "global_path_norm": 291.25820803884653,
        "timestamp": "2024-11-26T17:40:53.508181"
    },
    {
        "epoch": 2,
        "learning_rate": 0.01,
        "batch_size": 32,
        "len_train_indices": 10000,
        "len_test_indices": 2000,
        "momentum": 0.5,
        "train_loss": 0.02042607910493716,
        "train_accuracy": 99.63,
        "test_loss": 1.3012411854569874,
        "test_accuracy": 72.55,
        "path_norm": 182.3416264872067,
        "global_path_norm": 291.25820803884653,
        "timestamp": "2024-11-26T17:42:03.676199"
    },
    {
        "epoch": 0,
        "learning_rate": 0.01,
        "batch_size": 32,
        "len_train_indices": 10000,
        "len_test_indices": 2000,
        "momentum": 0.5,
        "train_loss": 0.08039145038787501,
        "train_accuracy": 97.15,
        "test_loss": 1.4396907933174619,
        "test_accuracy": 72.35,
        "path_norm": 223.7179097099738,
        "global_path_norm": 507.58386006649187,
        "timestamp": "2024-11-26T17:44:05.505599"
    },
    {
        "epoch": 1,
        "learning_rate": 0.01,
        "batch_size": 32,
        "len_train_indices": 10000,
        "len_test_indices": 2000,
        "momentum": 0.5,
        "train_loss": 0.026160537512019313,
        "train_accuracy": 99.32,
        "test_loss": 1.4019285028889066,
        "test_accuracy": 72.85,
        "path_norm": 228.61971187159256,
        "global_path_norm": 507.58386006649187,
        "timestamp": "2024-11-26T17:45:19.253147"
    },
    {
        "epoch": 2,
        "learning_rate": 0.01,
        "batch_size": 32,
        "len_train_indices": 10000,
        "len_test_indices": 2000,
        "momentum": 0.5,
        "train_loss": 0.012736192088761625,
        "train_accuracy": 99.73,
        "test_loss": 1.3337705807080344,
        "test_accuracy": 74.0,
        "path_norm": 226.5967905084933,
        "global_path_norm": 507.58386006649187,
        "timestamp": "2024-11-26T17:46:29.203119"
    },
    {
        "epoch": 0,
        "learning_rate": 0.01,
        "batch_size": 32,
        "len_train_indices": 10000,
        "len_test_indices": 2000,
        "momentum": 0.5,
        "train_loss": 0.04772614241918376,
        "train_accuracy": 98.31,
        "test_loss": 1.598964598443773,
        "test_accuracy": 72.65,
        "path_norm": 283.244580155561,
        "global_path_norm": 854.012514545308,
        "timestamp": "2024-11-26T17:48:26.184539"
    },
    {
        "epoch": 1,
        "learning_rate": 0.01,
        "batch_size": 32,
        "len_train_indices": 10000,
        "len_test_indices": 2000,
        "momentum": 0.5,
        "train_loss": 0.018502705438157765,
        "train_accuracy": 99.49,
        "test_loss": 1.542211103060889,
        "test_accuracy": 73.7,
        "path_norm": 284.28115209682824,
        "global_path_norm": 854.012514545308,
        "timestamp": "2024-11-26T17:49:33.966498"
    },
    {
        "epoch": 2,
        "learning_rate": 0.01,
        "batch_size": 32,
        "len_train_indices": 10000,
        "len_test_indices": 2000,
        "momentum": 0.5,
        "train_loss": 0.008265636137122447,
        "train_accuracy": 99.88,
        "test_loss": 1.6208538857717363,
        "test_accuracy": 72.75,
        "path_norm": 283.74004663159553,
        "global_path_norm": 854.012514545308,
        "timestamp": "2024-11-26T17:50:42.083737"
    },
    {
        "epoch": 0,
        "learning_rate": 0.01,
        "batch_size": 32,
        "len_train_indices": 10000,
        "len_test_indices": 2000,
        "momentum": 0.5,
        "train_loss": 0.03807239954809125,
        "train_accuracy": 98.52,
        "test_loss": 1.8101839555634394,
        "test_accuracy": 71.8,
        "path_norm": 355.2002296240812,
        "global_path_norm": 1375.760653238782,
        "timestamp": "2024-11-26T17:52:54.900622"
    },
    {
        "epoch": 1,
        "learning_rate": 0.01,
        "batch_size": 32,
        "len_train_indices": 10000,
        "len_test_indices": 2000,
        "momentum": 0.5,
        "train_loss": 0.017673637552451663,
        "train_accuracy": 99.42,
        "test_loss": 1.6914023326502905,
        "test_accuracy": 72.4,
        "path_norm": 354.9092203472601,
        "global_path_norm": 1375.760653238782,
        "timestamp": "2024-11-26T17:54:08.683907"
    },
    {
        "epoch": 2,
        "learning_rate": 0.01,
        "batch_size": 32,
        "len_train_indices": 10000,
        "len_test_indices": 2000,
        "momentum": 0.5,
        "train_loss": 0.008965404959383068,
        "train_accuracy": 99.78,
        "test_loss": 1.6774903597339752,
        "test_accuracy": 73.25,
        "path_norm": 350.87611328644186,
        "global_path_norm": 1375.760653238782,
        "timestamp": "2024-11-26T17:55:19.097240"
    },
    {
        "epoch": 0,
        "learning_rate": 0.01,
        "batch_size": 32,
        "len_train_indices": 10000,
        "len_test_indices": 2000,
        "momentum": 0.5,
        "train_loss": 0.02494019249486871,
        "train_accuracy": 99.18,
        "test_loss": 1.9025551506451197,
        "test_accuracy": 72.65,
        "path_norm": 435.91419740586565,
        "global_path_norm": 2116.66164041398,
        "timestamp": "2024-11-26T17:57:15.212767"
    },
    {
        "epoch": 1,
        "learning_rate": 0.01,
        "batch_size": 32,
        "len_train_indices": 10000,
        "len_test_indices": 2000,
        "momentum": 0.5,
        "train_loss": 0.010820491583932328,
        "train_accuracy": 99.76,
        "test_loss": 1.8344891875509233,
        "test_accuracy": 72.8,
        "path_norm": 427.8339339042662,
        "global_path_norm": 2116.66164041398,
        "timestamp": "2024-11-26T17:58:22.655707"
    },
    {
        "epoch": 2,
        "learning_rate": 0.01,
        "batch_size": 32,
        "len_train_indices": 10000,
        "len_test_indices": 2000,
        "momentum": 0.5,
        "train_loss": 0.00693494642808265,
        "train_accuracy": 99.8,
        "test_loss": 1.879495394608331,
        "test_accuracy": 72.95,
        "path_norm": 435.45665685576563,
        "global_path_norm": 2116.66164041398,
        "timestamp": "2024-11-26T17:59:30.116380"
    },
    {
        "epoch": 0,
        "learning_rate": 0.01,
        "batch_size": 32,
        "len_train_indices": 10000,
        "len_test_indices": 2000,
        "momentum": 0.5,
        "train_loss": 0.019506365899354578,
        "train_accuracy": 99.39,
        "test_loss": 1.914915504909697,
        "test_accuracy": 72.65,
        "path_norm": 522.3097739847494,
        "global_path_norm": 3113.658137946425,
        "timestamp": "2024-11-26T18:01:43.052684"
    },
    {
        "epoch": 1,
        "learning_rate": 0.01,
        "batch_size": 32,
        "len_train_indices": 10000,
        "len_test_indices": 2000,
        "momentum": 0.5,
        "train_loss": 0.008347648770967107,
        "train_accuracy": 99.73,
        "test_loss": 1.8843581113550398,
        "test_accuracy": 73.05,
        "path_norm": 529.1439135528254,
        "global_path_norm": 3113.658137946425,
        "timestamp": "2024-11-26T18:02:57.206112"
    },
    {
        "epoch": 2,
        "learning_rate": 0.01,
        "batch_size": 32,
        "len_train_indices": 10000,
        "len_test_indices": 2000,
        "momentum": 0.5,
        "train_loss": 0.007897901192999083,
        "train_accuracy": 99.73,
        "test_loss": 1.9036733839246962,
        "test_accuracy": 73.25,
        "path_norm": 524.6289164733488,
        "global_path_norm": 3113.658137946425,
        "timestamp": "2024-11-26T18:04:08.772454"
    },
    {
        "epoch": 0,
        "learning_rate": 0.01,
        "batch_size": 32,
        "len_train_indices": 10000,
        "len_test_indices": 2000,
        "momentum": 0.5,
        "train_loss": 0.019316061190513135,
        "train_accuracy": 99.26,
        "test_loss": 1.9744774921545907,
        "test_accuracy": 72.8,
        "path_norm": 629.5329618058137,
        "global_path_norm": 4395.45720033764,
        "timestamp": "2024-11-26T18:06:10.536676"
    },
    {
        "epoch": 1,
        "learning_rate": 0.01,
        "batch_size": 32,
        "len_train_indices": 10000,
        "len_test_indices": 2000,
        "momentum": 0.5,
        "train_loss": 0.008412773001437134,
        "train_accuracy": 99.7,
        "test_loss": 1.95089557530388,
        "test_accuracy": 73.7,
        "path_norm": 622.949084998124,
        "global_path_norm": 4395.45720033764,
        "timestamp": "2024-11-26T18:07:24.452105"
    },
    {
        "epoch": 2,
        "learning_rate": 0.01,
        "batch_size": 32,
        "len_train_indices": 10000,
        "len_test_indices": 2000,
        "momentum": 0.5,
        "train_loss": 0.007007521211466672,
        "train_accuracy": 99.78,
        "test_loss": 1.9308792045192114,
        "test_accuracy": 73.7,
        "path_norm": 629.7374452897017,
        "global_path_norm": 4395.45720033764,
        "timestamp": "2024-11-26T18:08:35.320394"
    },
    {
        "epoch": 0,
        "learning_rate": 0.01,
        "batch_size": 32,
        "len_train_indices": 10000,
        "len_test_indices": 2000,
        "momentum": 0.5,
        "train_loss": 0.013355011531396517,
        "train_accuracy": 99.56,
        "test_loss": 1.9869962060262287,
        "test_accuracy": 74.2,
        "path_norm": 733.8555716215556,
        "global_path_norm": 5976.322615120439,
        "timestamp": "2024-11-26T18:10:35.301052"
    },
    {
        "epoch": 1,
        "learning_rate": 0.01,
        "batch_size": 32,
        "len_train_indices": 10000,
        "len_test_indices": 2000,
        "momentum": 0.5,
        "train_loss": 0.008661369802490944,
        "train_accuracy": 99.67,
        "test_loss": 2.0859685284750804,
        "test_accuracy": 72.7,
        "path_norm": 735.6422364165886,
        "global_path_norm": 5976.322615120439,
        "timestamp": "2024-11-26T18:11:49.385692"
    },
    {
        "epoch": 2,
        "learning_rate": 0.01,
        "batch_size": 32,
        "len_train_indices": 10000,
        "len_test_indices": 2000,
        "momentum": 0.5,
        "train_loss": 0.006710023003776882,
        "train_accuracy": 99.82,
        "test_loss": 2.0794047533519686,
        "test_accuracy": 73.5,
        "path_norm": 742.3610560232804,
        "global_path_norm": 5976.322615120439,
        "timestamp": "2024-11-26T18:12:59.535867"
    },
    {
        "epoch": 0,
        "learning_rate": 0.01,
        "batch_size": 32,
        "len_train_indices": 10000,
        "len_test_indices": 2000,
        "momentum": 0.5,
        "train_loss": 0.013730023756605763,
        "train_accuracy": 99.53,
        "test_loss": 2.101951037607496,
        "test_accuracy": 74.25,
        "path_norm": 846.1267266196004,
        "global_path_norm": 7853.270656229798,
        "timestamp": "2024-11-26T18:15:00.949695"
    },
    {
        "epoch": 1,
        "learning_rate": 0.01,
        "batch_size": 32,
        "len_train_indices": 10000,
        "len_test_indices": 2000,
        "momentum": 0.5,
        "train_loss": 0.00595468769558782,
        "train_accuracy": 99.81,
        "test_loss": 2.075845451108993,
        "test_accuracy": 74.55,
        "path_norm": 850.5625344441172,
        "global_path_norm": 7853.270656229798,
        "timestamp": "2024-11-26T18:16:14.927912"
    },
    {
        "epoch": 2,
        "learning_rate": 0.01,
        "batch_size": 32,
        "len_train_indices": 10000,
        "len_test_indices": 2000,
        "momentum": 0.5,
        "train_loss": 0.005875527361222368,
        "train_accuracy": 99.8,
        "test_loss": 2.1205185576090737,
        "test_accuracy": 73.85,
        "path_norm": 842.7335358818942,
        "global_path_norm": 7853.270656229798,
        "timestamp": "2024-11-26T18:17:24.271797"
    },
    {
        "epoch": 0,
        "learning_rate": 0.01,
        "batch_size": 32,
        "len_train_indices": 10000,
        "len_test_indices": 2000,
        "momentum": 0.5,
        "train_loss": 0.011868207097550315,
        "train_accuracy": 99.58,
        "test_loss": 2.1428370456846935,
        "test_accuracy": 75.25,
        "path_norm": 958.5886435275561,
        "global_path_norm": 10011.381523046657,
        "timestamp": "2024-11-26T18:19:25.822634"
    },
    {
        "epoch": 1,
        "learning_rate": 0.01,
        "batch_size": 32,
        "len_train_indices": 10000,
        "len_test_indices": 2000,
        "momentum": 0.5,
        "train_loss": 0.006389522978988912,
        "train_accuracy": 99.73,
        "test_loss": 2.1668475118894426,
        "test_accuracy": 75.1,
        "path_norm": 969.1801625600888,
        "global_path_norm": 10011.381523046657,
        "timestamp": "2024-11-26T18:20:39.736844"
    },
    {
        "epoch": 2,
        "learning_rate": 0.01,
        "batch_size": 32,
        "len_train_indices": 10000,
        "len_test_indices": 2000,
        "momentum": 0.5,
        "train_loss": 0.0036797888214707675,
        "train_accuracy": 99.89,
        "test_loss": 2.1623980715161277,
        "test_accuracy": 75.35,
        "path_norm": 963.8956115679747,
        "global_path_norm": 10011.381523046657,
        "timestamp": "2024-11-26T18:21:49.778640"
    },
    {
        "epoch": 0,
        "learning_rate": 0.01,
        "batch_size": 32,
        "len_train_indices": 10000,
        "len_test_indices": 2000,
        "momentum": 0.5,
        "train_loss": 0.009195030451381103,
        "train_accuracy": 99.67,
        "test_loss": 2.166553781146095,
        "test_accuracy": 74.8,
        "path_norm": 1085.704782618185,
        "global_path_norm": 12423.295537014323,
        "timestamp": "2024-11-26T18:23:49.747599"
    },
    {
        "epoch": 1,
        "learning_rate": 0.01,
        "batch_size": 32,
        "len_train_indices": 10000,
        "len_test_indices": 2000,
        "momentum": 0.5,
        "train_loss": 0.005309577838125405,
        "train_accuracy": 99.83,
        "test_loss": 2.1705118171752447,
        "test_accuracy": 75.15,
        "path_norm": 1091.5985411313081,
        "global_path_norm": 12423.295537014323,
        "timestamp": "2024-11-26T18:25:03.685128"
    },
    {
        "epoch": 2,
        "learning_rate": 0.01,
        "batch_size": 32,
        "len_train_indices": 10000,
        "len_test_indices": 2000,
        "momentum": 0.5,
        "train_loss": 0.003791698148937178,
        "train_accuracy": 99.84,
        "test_loss": 2.168455644259377,
        "test_accuracy": 74.45,
        "path_norm": 1097.4346221985163,
        "global_path_norm": 12423.295537014323,
        "timestamp": "2024-11-26T18:26:13.888578"
    },
    {
        "epoch": 0,
        "learning_rate": 0.01,
        "batch_size": 32,
        "len_train_indices": 10000,
        "len_test_indices": 2000,
        "momentum": 0.5,
        "train_loss": 0.006928883538278979,
        "train_accuracy": 99.75,
        "test_loss": 2.1498799219964044,
        "test_accuracy": 75.3,
        "path_norm": 1209.677436344086,
        "global_path_norm": 15054.45050475108,
        "timestamp": "2024-11-26T18:28:11.331701"
    },
    {
        "epoch": 1,
        "learning_rate": 0.01,
        "batch_size": 32,
        "len_train_indices": 10000,
        "len_test_indices": 2000,
        "momentum": 0.5,
        "train_loss": 0.0038130279882547307,
        "train_accuracy": 99.89,
        "test_loss": 2.199512010528928,
        "test_accuracy": 74.75,
        "path_norm": 1215.8752505911123,
        "global_path_norm": 15054.45050475108,
        "timestamp": "2024-11-26T18:29:20.026785"
    },
    {
        "epoch": 2,
        "learning_rate": 0.01,
        "batch_size": 32,
        "len_train_indices": 10000,
        "len_test_indices": 2000,
        "momentum": 0.5,
        "train_loss": 0.002499205385460325,
        "train_accuracy": 99.92,
        "test_loss": 2.1759077641699047,
        "test_accuracy": 75.2,
        "path_norm": 1216.445025473819,
        "global_path_norm": 15054.45050475108,
        "timestamp": "2024-11-26T18:30:28.714746"
    },
    {
        "epoch": 0,
        "learning_rate": 0.01,
        "batch_size": 32,
        "len_train_indices": 10000,
        "len_test_indices": 2000,
        "momentum": 0.5,
        "train_loss": 0.015379677080661165,
        "train_accuracy": 99.46,
        "test_loss": 2.273896810554323,
        "test_accuracy": 75.05,
        "path_norm": 1342.7173939440868,
        "global_path_norm": 17859.75139804583,
        "timestamp": "2024-11-26T18:32:39.484738"
    },
    {
        "epoch": 1,
        "learning_rate": 0.01,
        "batch_size": 32,
        "len_train_indices": 10000,
        "len_test_indices": 2000,
        "momentum": 0.5,
        "train_loss": 0.004895071270948102,
        "train_accuracy": 99.82,
        "test_loss": 2.268754489838131,
        "test_accuracy": 74.65,
        "path_norm": 1340.4108045670177,
        "global_path_norm": 17859.75139804583,
        "timestamp": "2024-11-26T18:33:53.574525"
    },
    {
        "epoch": 2,
        "learning_rate": 0.01,
        "batch_size": 32,
        "len_train_indices": 10000,
        "len_test_indices": 2000,
        "momentum": 0.5,
        "train_loss": 0.0031880184353413324,
        "train_accuracy": 99.93,
        "test_loss": 2.266968796177516,
        "test_accuracy": 74.9,
        "path_norm": 1345.0164032457003,
        "global_path_norm": 17859.75139804583,
        "timestamp": "2024-11-26T18:35:03.767155"
    },
    {
        "epoch": 0,
        "learning_rate": 0.01,
        "batch_size": 32,
        "len_train_indices": 10000,
        "len_test_indices": 2000,
        "momentum": 0.5,
        "train_loss": 0.008904510052861922,
        "train_accuracy": 99.75,
        "test_loss": 2.278672930740175,
        "test_accuracy": 74.85,
        "path_norm": 1460.7972138527648,
        "global_path_norm": 20780.611733055404,
        "timestamp": "2024-11-26T18:37:05.360875"
    },
    {
        "epoch": 1,
        "learning_rate": 0.01,
        "batch_size": 32,
        "len_train_indices": 10000,
        "len_test_indices": 2000,
        "momentum": 0.5,
        "train_loss": 0.006856519786183547,
        "train_accuracy": 99.76,
        "test_loss": 2.2690056926674314,
        "test_accuracy": 74.8,
        "path_norm": 1461.5287373158285,
        "global_path_norm": 20780.611733055404,
        "timestamp": "2024-11-26T18:38:19.437922"
    },
    {
        "epoch": 2,
        "learning_rate": 0.01,
        "batch_size": 32,
        "len_train_indices": 10000,
        "len_test_indices": 2000,
        "momentum": 0.5,
        "train_loss": 0.0036339701177683648,
        "train_accuracy": 99.92,
        "test_loss": 2.2371493629992956,
        "test_accuracy": 75.05,
        "path_norm": 1473.2728023010538,
        "global_path_norm": 20780.611733055404,
        "timestamp": "2024-11-26T18:39:28.540242"
    },
    {
        "epoch": 0,
        "learning_rate": 0.01,
        "batch_size": 32,
        "len_train_indices": 10000,
        "len_test_indices": 2000,
        "momentum": 0.5,
        "train_loss": 0.00783605083555607,
        "train_accuracy": 99.73,
        "test_loss": 2.2446116246874372,
        "test_accuracy": 74.95,
        "path_norm": 1603.1865144143399,
        "global_path_norm": 23782.899402722116,
        "timestamp": "2024-11-26T18:41:27.984941"
    },
    {
        "epoch": 1,
        "learning_rate": 0.01,
        "batch_size": 32,
        "len_train_indices": 10000,
        "len_test_indices": 2000,
        "momentum": 0.5,
        "train_loss": 0.005117142370825302,
        "train_accuracy": 99.82,
        "test_loss": 2.2768742527280534,
        "test_accuracy": 74.4,
        "path_norm": 1573.8859552076829,
        "global_path_norm": 23782.899402722116,
        "timestamp": "2024-11-26T18:42:41.987977"
    },
    {
        "epoch": 2,
        "learning_rate": 0.01,
        "batch_size": 32,
        "len_train_indices": 10000,
        "len_test_indices": 2000,
        "momentum": 0.5,
        "train_loss": 0.0025596215771087555,
        "train_accuracy": 99.92,
        "test_loss": 2.319855075033884,
        "test_accuracy": 74.6,
        "path_norm": 1589.4897766264494,
        "global_path_norm": 23782.899402722116,
        "timestamp": "2024-11-26T18:43:52.368548"
    },
    {
        "epoch": 0,
        "learning_rate": 0.01,
        "batch_size": 32,
        "len_train_indices": 10000,
        "len_test_indices": 2000,
        "momentum": 0.5,
        "train_loss": 0.005293388714883472,
        "train_accuracy": 99.75,
        "test_loss": 2.2967483008664753,
        "test_accuracy": 74.4,
        "path_norm": 1703.2582012131925,
        "global_path_norm": 26815.862768145274,
        "timestamp": "2024-11-26T18:45:53.568236"
    },
    {
        "epoch": 1,
        "learning_rate": 0.01,
        "batch_size": 32,
        "len_train_indices": 10000,
        "len_test_indices": 2000,
        "momentum": 0.5,
        "train_loss": 0.0037193816018452853,
        "train_accuracy": 99.9,
        "test_loss": 2.2668028454931957,
        "test_accuracy": 75.1,
        "path_norm": 1699.5830371005707,
        "global_path_norm": 26815.862768145274,
        "timestamp": "2024-11-26T18:47:07.796454"
    },
    {
        "epoch": 2,
        "learning_rate": 0.01,
        "batch_size": 32,
        "len_train_indices": 10000,
        "len_test_indices": 2000,
        "momentum": 0.5,
        "train_loss": 0.004614659812672451,
        "train_accuracy": 99.89,
        "test_loss": 2.3534604963802157,
        "test_accuracy": 74.35,
        "path_norm": 1696.3510839445944,
        "global_path_norm": 26815.862768145274,
        "timestamp": "2024-11-26T18:48:18.519526"
    },
    {
        "epoch": 0,
        "learning_rate": 0.01,
        "batch_size": 32,
        "len_train_indices": 10000,
        "len_test_indices": 2000,
        "momentum": 0.5,
        "train_loss": 0.007027976559832644,
        "train_accuracy": 99.76,
        "test_loss": 2.28333348319644,
        "test_accuracy": 74.85,
        "path_norm": 1802.009017735483,
        "global_path_norm": 29840.12546890512,
        "timestamp": "2024-11-26T18:50:20.812192"
    },
    {
        "epoch": 1,
        "learning_rate": 0.01,
        "batch_size": 32,
        "len_train_indices": 10000,
        "len_test_indices": 2000,
        "momentum": 0.5,
        "train_loss": 0.0036619424947804753,
        "train_accuracy": 99.87,
        "test_loss": 2.2911727560891046,
        "test_accuracy": 75.05,
        "path_norm": 1791.4526228734044,
        "global_path_norm": 29840.12546890512,
        "timestamp": "2024-11-26T18:51:34.852453"
    },
    {
        "epoch": 2,
        "learning_rate": 0.01,
        "batch_size": 32,
        "len_train_indices": 10000,
        "len_test_indices": 2000,
        "momentum": 0.5,
        "train_loss": 0.003123430741699047,
        "train_accuracy": 99.9,
        "test_loss": 2.2174411264676896,
        "test_accuracy": 75.55,
        "path_norm": 1785.5639865319865,
        "global_path_norm": 29840.12546890512,
        "timestamp": "2024-11-26T18:52:44.972503"
    },
    {
        "epoch": 0,
        "learning_rate": 0.01,
        "batch_size": 32,
        "len_train_indices": 10000,
        "len_test_indices": 2000,
        "momentum": 0.5,
        "train_loss": 0.005095191237297112,
        "train_accuracy": 99.82,
        "test_loss": 2.3259317193712508,
        "test_accuracy": 75.45,
        "path_norm": 1900.3169472485372,
        "global_path_norm": 32797.85163695939,
        "timestamp": "2024-11-26T18:54:43.697940"
    },
    {
        "epoch": 1,
        "learning_rate": 0.01,
        "batch_size": 32,
        "len_train_indices": 10000,
        "len_test_indices": 2000,
        "momentum": 0.5,
        "train_loss": 0.003557958632169951,
        "train_accuracy": 99.9,
        "test_loss": 2.3167331876262787,
        "test_accuracy": 75.35,
        "path_norm": 1894.719570279465,
        "global_path_norm": 32797.85163695939,
        "timestamp": "2024-11-26T18:55:57.644812"
    },
    {
        "epoch": 2,
        "learning_rate": 0.01,
        "batch_size": 32,
        "len_train_indices": 10000,
        "len_test_indices": 2000,
        "momentum": 0.5,
        "train_loss": 0.0021805471677066707,
        "train_accuracy": 99.93,
        "test_loss": 2.286851965718799,
        "test_accuracy": 75.05,
        "path_norm": 1887.2207740484419,
        "global_path_norm": 32797.85163695939,
        "timestamp": "2024-11-26T18:57:09.038362"
    },
    {
        "epoch": 0,
        "learning_rate": 0.01,
        "batch_size": 32,
        "len_train_indices": 10000,
        "len_test_indices": 2000,
        "momentum": 0.5,
        "train_loss": 0.0038707606452064395,
        "train_accuracy": 99.86,
        "test_loss": 2.381815850261658,
        "test_accuracy": 74.9,
        "path_norm": 2038.7252757544356,
        "global_path_norm": 35666.542753678834,
        "timestamp": "2024-11-26T18:59:11.231471"
    },
    {
        "epoch": 1,
        "learning_rate": 0.01,
        "batch_size": 32,
        "len_train_indices": 10000,
        "len_test_indices": 2000,
        "momentum": 0.5,
        "train_loss": 0.0035989960223290905,
        "train_accuracy": 99.89,
        "test_loss": 2.370042301359631,
        "test_accuracy": 74.7,
        "path_norm": 2019.300992918094,
        "global_path_norm": 35666.542753678834,
        "timestamp": "2024-11-26T19:00:25.204840"
    },
    {
        "epoch": 2,
        "learning_rate": 0.01,
        "batch_size": 32,
        "len_train_indices": 10000,
        "len_test_indices": 2000,
        "momentum": 0.5,
        "train_loss": 0.0034875742387249047,
        "train_accuracy": 99.9,
        "test_loss": 2.36828513183291,
        "test_accuracy": 74.7,
        "path_norm": 2037.725202278266,
        "global_path_norm": 35666.542753678834,
        "timestamp": "2024-11-26T19:01:36.190816"
    },
    {
        "epoch": 0,
        "learning_rate": 0.01,
        "batch_size": 32,
        "len_train_indices": 10000,
        "len_test_indices": 2000,
        "momentum": 0.5,
        "train_loss": 0.0056311115530383255,
        "train_accuracy": 99.83,
        "test_loss": 2.4216682106729537,
        "test_accuracy": 74.6,
        "path_norm": 2094.4833491818454,
        "global_path_norm": 38426.289334256566,
        "timestamp": "2024-11-26T19:03:39.170322"
    },
    {
        "epoch": 1,
        "learning_rate": 0.01,
        "batch_size": 32,
        "len_train_indices": 10000,
        "len_test_indices": 2000,
        "momentum": 0.5,
        "train_loss": 0.0031268612517243665,
        "train_accuracy": 99.9,
        "test_loss": 2.354064579047854,
        "test_accuracy": 75.2,
        "path_norm": 2107.9577794633365,
        "global_path_norm": 38426.289334256566,
        "timestamp": "2024-11-26T19:04:52.770605"
    },
    {
        "epoch": 2,
        "learning_rate": 0.01,
        "batch_size": 32,
        "len_train_indices": 10000,
        "len_test_indices": 2000,
        "momentum": 0.5,
        "train_loss": 0.0028995006849598464,
        "train_accuracy": 99.92,
        "test_loss": 2.3778500651556347,
        "test_accuracy": 75.25,
        "path_norm": 2115.6106683414127,
        "global_path_norm": 38426.289334256566,
        "timestamp": "2024-11-26T19:06:02.043412"
    },
    {
        "epoch": 0,
        "learning_rate": 0.01,
        "batch_size": 32,
        "len_train_indices": 10000,
        "len_test_indices": 2000,
        "momentum": 0.5,
        "train_loss": 0.005636551142345342,
        "train_accuracy": 99.84,
        "test_loss": 2.4236256631593855,
        "test_accuracy": 75.25,
        "path_norm": 2211.1941343988774,
        "global_path_norm": 41047.26329488971,
        "timestamp": "2024-11-26T19:08:04.409428"
    },
    {
        "epoch": 1,
        "learning_rate": 0.01,
        "batch_size": 32,
        "len_train_indices": 10000,
        "len_test_indices": 2000,
        "momentum": 0.5,
        "train_loss": 0.0018996675101046736,
        "train_accuracy": 99.94,
        "test_loss": 2.3884129382315136,
        "test_accuracy": 74.8,
        "path_norm": 2208.298213557218,
        "global_path_norm": 41047.26329488971,
        "timestamp": "2024-11-26T19:09:18.374625"
    },
    {
        "epoch": 2,
        "learning_rate": 0.01,
        "batch_size": 32,
        "len_train_indices": 10000,
        "len_test_indices": 2000,
        "momentum": 0.5,
        "train_loss": 0.002950883239694662,
        "train_accuracy": 99.89,
        "test_loss": 2.3644458613698442,
        "test_accuracy": 74.9,
        "path_norm": 2221.470571490876,
        "global_path_norm": 41047.26329488971,
        "timestamp": "2024-11-26T19:10:27.853430"
    },
    {
        "epoch": 0,
        "learning_rate": 0.01,
        "batch_size": 32,
        "len_train_indices": 10000,
        "len_test_indices": 2000,
        "momentum": 0.5,
        "train_loss": 0.0048502391290216424,
        "train_accuracy": 99.85,
        "test_loss": 2.44737941783572,
        "test_accuracy": 74.9,
        "path_norm": 2291.401863488812,
        "global_path_norm": 43526.280429184386,
        "timestamp": "2024-11-26T19:12:23.859548"
    },
    {
        "epoch": 1,
        "learning_rate": 0.01,
        "batch_size": 32,
        "len_train_indices": 10000,
        "len_test_indices": 2000,
        "momentum": 0.5,
        "train_loss": 0.0028066773954731777,
        "train_accuracy": 99.91,
        "test_loss": 2.4225317533645363,
        "test_accuracy": 75.0,
        "path_norm": 2315.6766829590006,
        "global_path_norm": 43526.280429184386,
        "timestamp": "2024-11-26T19:13:32.069334"
    },
    {
        "epoch": 2,
        "learning_rate": 0.01,
        "batch_size": 32,
        "len_train_indices": 10000,
        "len_test_indices": 2000,
        "momentum": 0.5,
        "train_loss": 0.0019508440316607343,
        "train_accuracy": 99.95,
        "test_loss": 2.398670401838091,
        "test_accuracy": 75.0,
        "path_norm": 2304.706922799513,
        "global_path_norm": 43526.280429184386,
        "timestamp": "2024-11-26T19:14:40.438509"
    },
    {
        "epoch": 0,
        "learning_rate": 0.01,
        "batch_size": 32,
        "len_train_indices": 10000,
        "len_test_indices": 2000,
        "momentum": 0.5,
        "train_loss": 0.0045249035091637566,
        "train_accuracy": 99.81,
        "test_loss": 2.4383595789235737,
        "test_accuracy": 75.0,
        "path_norm": 2388.9268511195564,
        "global_path_norm": 45852.95733101628,
        "timestamp": "2024-11-26T19:16:53.685338"
    },
    {
        "epoch": 1,
        "learning_rate": 0.01,
        "batch_size": 32,
        "len_train_indices": 10000,
        "len_test_indices": 2000,
        "momentum": 0.5,
        "train_loss": 0.0022947903002733866,
        "train_accuracy": 99.93,
        "test_loss": 2.4048704105237175,
        "test_accuracy": 75.2,
        "path_norm": 2388.9096885399413,
        "global_path_norm": 45852.95733101628,
        "timestamp": "2024-11-26T19:18:07.623900"
    },
    {
        "epoch": 2,
        "learning_rate": 0.01,
        "batch_size": 32,
        "len_train_indices": 10000,
        "len_test_indices": 2000,
        "momentum": 0.5,
        "train_loss": 0.002730830211730202,
        "train_accuracy": 99.93,
        "test_loss": 2.438143459577409,
        "test_accuracy": 75.2,
        "path_norm": 2411.9714965148323,
        "global_path_norm": 45852.95733101628,
        "timestamp": "2024-11-26T19:19:17.125820"
    }
]